mbutil_zyx/__init__.py
mbutil_zyx/util.py
mbutil_zyx-0.4.2.dist-info/LICENSE.md
mbutil_zyx-0.4.2.dist-info/METADATA
mbutil_zyx-0.4.2.dist-info/WHEEL
mbutil_zyx-0.4.2.dist-info/top_level.txt
mbutil_zyx-0.4.2.dist-info/RECORD
