Metadata-Version: 2.1
Name: mbutil_zyx
Version: 0.4.2
Summary: MBUtil with ZYX scheme
Author: Lars Maxfield
License: Copyright (c), Development Seed  
Project-URL: Homepage, https://github.com/larsmaxfield/mbutil_zyx
Project-URL: Issues, https://github.com/larsmaxfield/mbutil_zyx
Keywords: mbutil,zyx,vips,libvips,pyvips,dzsave
Classifier: Programming Language :: Python
Classifier: License :: OSI Approved :: BSD License
Classifier: Operating System :: OS Independent
Requires-Python: >=3
License-File: LICENSE.md
